rest_framework_jwt/__init__.py
rest_framework_jwt/authentication.py
rest_framework_jwt/compat.py
rest_framework_jwt/locale/en_US/LC_MESSAGES/django.po
rest_framework_jwt/locale/fi/LC_MESSAGES/django.po
rest_framework_jwt/models.py
rest_framework_jwt/serializers.py
rest_framework_jwt/settings.py
rest_framework_jwt/test.py
rest_framework_jwt/utils.py
rest_framework_jwt/views.py
djangorestframework_jwt_treet-1.15.0.dist-info/LICENSE
djangorestframework_jwt_treet-1.15.0.dist-info/METADATA
djangorestframework_jwt_treet-1.15.0.dist-info/WHEEL
djangorestframework_jwt_treet-1.15.0.dist-info/RECORD
