Metadata-Version: 2.1
Name: djangorestframework-jwt-treet
Version: 1.15.0
Summary: JSON Web Token Authentication support for Django REST Framework
Author: José Padilla
Requires-Python: >=3.9,<4.0
Classifier: Programming Language :: Python :: 3
Classifier: Programming Language :: Python :: 3.9
Classifier: Programming Language :: Python :: 3.10
Classifier: Programming Language :: Python :: 3.11
Classifier: Programming Language :: Python :: 3.12
Classifier: Programming Language :: Python :: 3.13
Requires-Dist: pyjwt (>=2.0.0,<3.0.0)
